sourcetypes/__init__.py
sourcetypes/py.typed
sourcetypes3-0.1.0.dist-info/licenses/LICENSE
sourcetypes3-0.1.0.dist-info/METADATA
sourcetypes3-0.1.0.dist-info/WHEEL
sourcetypes3-0.1.0.dist-info/top_level.txt
sourcetypes3-0.1.0.dist-info/RECORD
