Metadata-Version: 2.4
Name: sourcetypes3
Version: 0.1.0
Summary: Python Source Code Types For Inline Syntax Highlighting
Author: Aurin Aegerter, Juro Oravec, Sam Willis
License-Expression: MIT
Project-URL: Homepage, https://github.com/chrxer/python-inline-source-3
Project-URL: Issues, https://github.com/chrxer/python-inline-source-3/issues
Classifier: Programming Language :: Python :: 3
Classifier: Operating System :: OS Independent
Requires-Python: >=3.8
License-File: LICENSE
Requires-Dist: typing-extensions>=3.7.4
Dynamic: license-file
